zeroshot_database/__init__.py
zeroshot_database/main.py
zeroshot_database-0.1.1.dist-info/METADATA
zeroshot_database-0.1.1.dist-info/WHEEL
zeroshot_database-0.1.1.dist-info/top_level.txt
zeroshot_database-0.1.1.dist-info/RECORD
